{
  "schemaVersion": 1,
  "taskId": "T03",
  "unitId": "M002/S04/T03",
  "timestamp": 1778651327303,
  "passed": false,
  "discoverySource": "task-plan",
  "checks": [
    {
      "command": "grep -c '^## ' docs/architecture.md",
      "exitCode": 4294967295,
      "durationMs": 204,
      "verdict": "fail"
    },
    {
      "command": "grep -c '^## ' docs/development-notes.md",
      "exitCode": 4294967295,
      "durationMs": 200,
      "verdict": "fail"
    }
  ],
  "retryAttempt": 1,
  "maxRetries": 2
}
